README.md
setup.cfg
setup.py
chance_paddy.egg-info/PKG-INFO
chance_paddy.egg-info/SOURCES.txt
chance_paddy.egg-info/dependency_links.txt
chance_paddy.egg-info/not-zip-safe
chance_paddy.egg-info/requires.txt
chance_paddy.egg-info/top_level.txt
paddy/__init__.py
paddy/constant.py
paddy/exceptions.py
paddy/trader.py
paddy/mode/__init__.py
paddy/mode/test_trader.py
paddy/mode/trade_easy.py
paddy/models/__init__.py
paddy/models/account.py
paddy/models/entrust.py
tests/__init__.py
tests/test_account.py
tests/test_entrust.py
tests/test_exceptions.py
tests/test_trade_easy.py
tests/test_trader.py