Metadata-Version: 1.0
Name: chance-paddy
Version: 1.2.1
Summary: The base trader for chancefocus
Home-page: https://gitee.com/QianFuFinancial/paddy.git
Author: Jimin Huang
Author-email: huangjimin@whu.edu.cn
License: MIT
Platform: UNKNOWN
